{"cameraMode":{"drawMode":0,"name":"Shaded","section":"Shading Mode"},"sceneLighting":true,"audioPlay":false,"sceneViewState":{"showFog":true,"showMaterialUpdate":false,"showSkybox":true,"showFlares":true,"showImageEffects":true,"showParticleSystems":true},"in2DMode":false,"pivot":{"x":-1.224779725074768,"y":-0.7969305515289307,"z":2.2973170280456545},"rotation":{"x":0.16218428313732148,"y":-0.30358925461769106,"z":0.05251786857843399,"w":0.9374380111694336},"size":8.660810470581055,"orthographic":false}